sai_pygame/__init__.py
sai_pygame/coop_puzzle/__init__.py
sai_pygame/coop_puzzle/coop_puzzle.py
sai_pygame/coop_puzzle/assets/__init__.py
sai_pygame/coop_puzzle/assets/circular-outline.png
sai_pygame/coop_puzzle/assets/square-black-outline.png
sai_pygame/coop_puzzle/assets/environment/cheese.png
sai_pygame/coop_puzzle/assets/environment/grass--1.png
sai_pygame/coop_puzzle/assets/environment/grass--2.png
sai_pygame/coop_puzzle/assets/environment/grass--3.png
sai_pygame/coop_puzzle/assets/environment/grass--4.png
sai_pygame/coop_puzzle/assets/environment/grass--5.png
sai_pygame/coop_puzzle/assets/environment/grass-shadow.png
sai_pygame/coop_puzzle/assets/environment/wall.png
sai_pygame/coop_puzzle/assets/flowers/flower-blue.png
sai_pygame/coop_puzzle/assets/flowers/flower-orange.png
sai_pygame/coop_puzzle/assets/flowers/flower-pink.png
sai_pygame/coop_puzzle/assets/flowers/flower-red.png
sai_pygame/coop_puzzle/assets/flowers/flower-white.png
sai_pygame/coop_puzzle/assets/player1/run-down-1.png
sai_pygame/coop_puzzle/assets/player1/run-down-2.png
sai_pygame/coop_puzzle/assets/player1/run-side-1.png
sai_pygame/coop_puzzle/assets/player1/run-side-2.png
sai_pygame/coop_puzzle/assets/player1/run-up-1.png
sai_pygame/coop_puzzle/assets/player1/run-up-2.png
sai_pygame/coop_puzzle/assets/player1/stopped.png
sai_pygame/coop_puzzle/assets/player2/run-down-1.png
sai_pygame/coop_puzzle/assets/player2/run-down-2.png
sai_pygame/coop_puzzle/assets/player2/run-side-1.png
sai_pygame/coop_puzzle/assets/player2/run-side-2.png
sai_pygame/coop_puzzle/assets/player2/run-up-1.png
sai_pygame/coop_puzzle/assets/player2/run-up-2.png
sai_pygame/coop_puzzle/assets/player2/stopped.png
sai_pygame/coop_puzzle/assets/shrubs/shrub-blue--1.png
sai_pygame/coop_puzzle/assets/shrubs/shrub-blue--2.png
sai_pygame/coop_puzzle/assets/shrubs/shrub-blue--3.png
sai_pygame/coop_puzzle/assets/shrubs/shrub-orange--1.png
sai_pygame/coop_puzzle/assets/shrubs/shrub-orange--2.png
sai_pygame-0.1.8.dist-info/METADATA
sai_pygame-0.1.8.dist-info/WHEEL
sai_pygame-0.1.8.dist-info/licenses/LICENSE
sai_pygame-0.1.8.dist-info/RECORD
