Metadata-Version: 2.4
Name: sai-pygame
Version: 0.1.8
Summary: A collection of pygame based minigame environments for the SAI platform.
Project-URL: Homepage, https://competesai.com
Project-URL: Documentation, https://docs.competesai.com
Author-email: ArenaX Labs <research@competesai.com>
License: MIT
License-File: LICENSE
Classifier: Programming Language :: Python :: 3
Classifier: Programming Language :: Python :: 3.10
Classifier: Programming Language :: Python :: 3.11
Classifier: Programming Language :: Python :: 3.12
Requires-Python: >=3.10
Requires-Dist: gymnasium<1.2.0,>=1.0.0
Requires-Dist: numpy<3.0,>=2.0.0
Requires-Dist: pygame<3,>=2.1.0
Requires-Dist: setuptools<71
